csify/__init__.py
csify/csify.py
csify-1.0.6.dist-info/METADATA
csify-1.0.6.dist-info/WHEEL
csify-1.0.6.dist-info/licenses/LICENSE
csify-1.0.6.dist-info/RECORD
