Metadata-Version: 2.1
Name: csify
Version: 1.0.6
Summary: Generate code-switched texts from monolingual texts
Project-URL: Source Code, https://github.com/Selubi/CSify
Project-URL: Bug Tracker, https://github.com/Selubi/CSify/issues
Author-email: Bryan Gregorius <contact@selubi.tech>
License-File: LICENSE
Keywords: code-switching,corpus generation,natural language processing
Classifier: Intended Audience :: Developers
Classifier: Intended Audience :: Science/Research
Classifier: License :: OSI Approved :: MIT License
Classifier: Natural Language :: English
Classifier: Natural Language :: Japanese
Classifier: Operating System :: OS Independent
Classifier: Programming Language :: Python :: 3
Requires-Python: >=3.7
Requires-Dist: spacy
